askcpg/__init__.py
askcpg/server.py
mcp_askcpg-0.1.5.dist-info/METADATA
mcp_askcpg-0.1.5.dist-info/WHEEL
mcp_askcpg-0.1.5.dist-info/entry_points.txt
mcp_askcpg-0.1.5.dist-info/RECORD
